streamlit_clickable_images/__init__.py
streamlit_clickable_images/frontend/index.html
streamlit_clickable_images/frontend/main.js
streamlit_clickable_images/frontend/streamlit-component-lib.js
streamlit_clickable_images/frontend/style.css
streamlit_button_with_images_and_links-0.1.4.dist-info/LICENSE
streamlit_button_with_images_and_links-0.1.4.dist-info/METADATA
streamlit_button_with_images_and_links-0.1.4.dist-info/WHEEL
streamlit_button_with_images_and_links-0.1.4.dist-info/top_level.txt
streamlit_button_with_images_and_links-0.1.4.dist-info/RECORD
