Metadata-Version: 2.1
Name: streamlit_button_with_images_and_links
Version: 0.1.4
Summary: Streamlit component which should allow you to replace buttons with images with caption
Author: Usman DG
Author-email: dimausman@inbox.ru
Requires-Python: >=3.7
License-File: LICENSE
Requires-Dist: streamlit>=1.2
Requires-Dist: jinja2
